corelab/__init__.py
corelab/core3d.py
corelab-1.0.2.dist-info/METADATA
corelab-1.0.2.dist-info/WHEEL
corelab-1.0.2.dist-info/licenses/LICENSE
corelab-1.0.2.dist-info/RECORD
